ssoproject/__init__.py
ssoproject/asgi.py
ssoproject/settings.py
ssoproject/urls.py
ssoproject/wsgi.py
users/__init__.py
users/admin.py
users/apps.py
users/consts.py
users/models.py
users/tests.py
users/urls.py
users/views.py
users/migrations/__init__.py
single_sign_on_demo-0.2.dist-info/METADATA
single_sign_on_demo-0.2.dist-info/WHEEL
single_sign_on_demo-0.2.dist-info/top_level.txt
single_sign_on_demo-0.2.dist-info/RECORD
